{
  "users": [
    {
      "name": "Charles",
      "surname": "Belcher",
      "phone": "(304) 932-2120",
      "email": "BelcherCharles@yahoo.com",
      "password": "Kennedy",
      "companyId": 1,
      "hireDate": "",
      "userType": "employee",
      "isAdmin": true,
      "deptId": 1,
      "id": 1
    },
    {
      "id": 2,
      "name": "Kennedy",
      "surname": "Belcher",
      "email": "KB@KB.com",
      "phone": "(000) 000-0000",
      "address": "68 Heatherwood Dr.",
      "city": "South Charleston",
      "state": "WV",
      "zip": "25309",
      "hireDate": "2019-04-04T17:08:09.864Z",
      "password": "daddy1",
      "companyId": 1,
      "userType": "employee"
    },
    {
      "name": "Hallie",
      "surname": "Warnock",
      "email": "HW@company1.com",
      "phone": "(681) 888-3333",
      "address": "Hickory St.",
      "city": "South Charleston",
      "state": "WV",
      "zip": "25309",
      "companyId": 1,
      "hireDate": "2019-04-09T15:18:15.703Z",
      "userType": "employee",
      "password": "fVM3U1vD",
      "id": 3
    },
    {
      "id": 4,
      "name": "John",
      "surname": "Doe",
      "email": "JD@JD.com",
      "phone": "(111) 222-333",
      "address": "Somewhere",
      "city": "Some City",
      "state": "AZ",
      "zip": "15678",
      "clientSince": "2019-04-09T17:36:15.102Z",
      "companyId": 1,
      "userType": "client"
    }
  ],
  "tasks": [
    {
      "taskDesc": "Go Sell Some Shit!",
      "dueDate": "2019-04-19",
      "note": "",
      "isPriority": "",
      "isComplete": true,
      "type": "",
      "companyId": 1,
      "id": 1,
      "userId": 3
    },
    {
      "userId": 3,
      "id": 2,
      "taskDesc": "Task #16",
      "dueDate": "2019-04-30",
      "isPriority": false,
      "note": "Get up and do something!",
      "type": "Service",
      "isComplete": false,
      "companyId": 1
    }
  ],
  "empTasks": [],
  "companies": [
    {
      "companyName": "Almost Heaven Interiors",
      "id": 1
    }
  ],
  "departments": [
    {
      "departmentName": "Executive/Administrative",
      "id": 1
    }
  ]
}